timetosail/__init__.py
timetosail/core.py
timetosail/sqlalchemy.py
time_to_sail-0.1.0.dist-info/METADATA
time_to_sail-0.1.0.dist-info/WHEEL
time_to_sail-0.1.0.dist-info/RECORD
