Metadata-Version: 2.4
Name: time-to-sail
Version: 0.1.0
Summary: UTC-first datetime utilities for Python & ORMs: parse any tz, store as UTC, convert for display.
Project-URL: Homepage, https://example.com/time-to-sail
Project-URL: Repository, https://example.com/time-to-sail
Author: Sailor Interactive
License: MIT
Classifier: License :: OSI Approved :: MIT License
Classifier: Operating System :: OS Independent
Classifier: Programming Language :: Python :: 3
Requires-Python: >=3.9
Requires-Dist: python-dateutil>=2.8.2
Requires-Dist: tzdata>=2024.1; platform_system == 'Windows'
Provides-Extra: dev
Requires-Dist: build; extra == 'dev'
Requires-Dist: pytest>=7; extra == 'dev'
Requires-Dist: twine; extra == 'dev'
Provides-Extra: orm
Requires-Dist: sqlalchemy>=2.0; extra == 'orm'
